dato/__init__.py
dato/base.py
dato/plot.py
dato/process.py
dato/style.py
dato/utils.py
dato/ml/__init__.py
dato/ml/base.py
dato/ml/clf.py
dato/ml/encoders.py
dato/ml/preprocessing.py
dato/ml/reg.py
dato/plot/__init__.py
dato/plot/static.py
dato/process/__init__.py
dato/process/base.py
dato/process/dataframe.py
dato/process/groupby.py
dato/sampledata/__init__.py
dato/sampledata/datagen.py
dato/tests/__init__.py
dato/tests/fixtures.py
dato/tests/helpers.py
dato/tests/test_base.py
dato/tests/test_ml.py
dato/tests/test_process.py
dato/tests/test_style.py
dato/tests/test_utils.py
dato-0.0.1a3.dist-info/LICENSE
dato-0.0.1a3.dist-info/METADATA
dato-0.0.1a3.dist-info/WHEEL
dato-0.0.1a3.dist-info/top_level.txt
dato-0.0.1a3.dist-info/RECORD
