Metadata-Version: 2.1
Name: dato
Version: 0.0.1a3
Summary: Declarative syntactic sugar for data piping.
Home-page: https://github.com/dataframehq/dato
Author: Joseph Moon
Author-email: joseph@opendataframe.com
License: GPLv3
Keywords: pipe,declarative,python,data science
Platform: UNKNOWN
